.gitignore
CHANGES.txt
MANIFEST.in
README.txt
bootstrap.py
buildout.cfg
setup.py
isotoma/__init__.py
isotoma.recipe.zope2install.egg-info/PKG-INFO
isotoma.recipe.zope2install.egg-info/SOURCES.txt
isotoma.recipe.zope2install.egg-info/dependency_links.txt
isotoma.recipe.zope2install.egg-info/entry_points.txt
isotoma.recipe.zope2install.egg-info/namespace_packages.txt
isotoma.recipe.zope2install.egg-info/not-zip-safe
isotoma.recipe.zope2install.egg-info/requires.txt
isotoma.recipe.zope2install.egg-info/top_level.txt
isotoma/recipe/__init__.py
isotoma/recipe/zope2install/README.txt
isotoma/recipe/zope2install/__init__.py
isotoma/recipe/zope2install/tests/__init__.py
isotoma/recipe/zope2install/tests/test_docs.py