Metadata-Version: 1.0
Name: isotoma.recipe.zope2install
Version: 0.0
Summary: ZC Buildout recipe for installing Zope 2.
Home-page: http://github.com/isotoma/isotoma.recipe.zope2install
Author: John Carr
Author-email: john.carr@isotoma.com
License: ZPL 2.1
Keywords: zope2 buildout
Platform: UNKNOWN
Classifier: License :: OSI Approved :: Zope Public License
Classifier: Framework :: Buildout
Classifier: Framework :: Buildout :: Recipe
Classifier: Framework :: Plone
Classifier: Framework :: Zope2
Classifier: Programming Language :: Python
